pyha/__init__.py
pyha/applications/__init__.py
pyha/applications/dc_removal_limesdr/__init__.py
pyha/applications/dc_removal_limesdr/dc_removal_limesdr.py
pyha/applications/dc_removal_limesdr/tapper.py
pyha/applications/spectrogram_limesdr/__init__.py
pyha/applications/spectrogram_limesdr/spectrogram_limesdr.py
pyha/common/__init__.py
pyha/common/complex.py
pyha/common/context_managers.py
pyha/common/core.py
pyha/common/datavalid.py
pyha/common/fixed_point.py
pyha/common/ram.py
pyha/common/shift_register.py
pyha/common/util.py
pyha/common/data/__init__.py
pyha/common/data/data.py
pyha/conversion/__init__.py
pyha/conversion/conversion.py
pyha/conversion/redbaron_transforms.py
pyha/conversion/top_generator.py
pyha/conversion/type_transforms.py
pyha/cores/__init__.py
pyha/cores/util.py
pyha/cores/cordic/__init__.py
pyha/cores/cordic/core.py
pyha/cores/cordic/nco/__init__.py
pyha/cores/cordic/nco/nco.py
pyha/cores/cordic/to_polar/__init__.py
pyha/cores/cordic/to_polar/to_polar.py
pyha/cores/etc/__init__.py
pyha/cores/etc/counters.py
pyha/cores/etc/sdr.py
pyha/cores/fft/__init__.py
pyha/cores/fft/bitreversal_fftshift_avgpool/__init__.py
pyha/cores/fft/bitreversal_fftshift_avgpool/bitreversal_fftshift_avgpool.py
pyha/cores/fft/fft_core/__init__.py
pyha/cores/fft/fft_core/r2sdf.py
pyha/cores/fft/fft_core/dev/__init__.py
pyha/cores/fft/fft_core/dev/reference.py
pyha/cores/fft/fft_power/__init__.py
pyha/cores/fft/fft_power/fft_power.py
pyha/cores/fft/spectrogram/__init__.py
pyha/cores/fft/spectrogram/spectrogram.py
pyha/cores/fft/windower/__init__.py
pyha/cores/fft/windower/windower.py
pyha/cores/filter/__init__.py
pyha/cores/filter/dc_removal/__init__.py
pyha/cores/filter/dc_removal/dc_removal.py
pyha/cores/filter/fir/__init__.py
pyha/cores/filter/fir/fir.py
pyha/cores/filter/moving_average/__init__.py
pyha/cores/filter/moving_average/moving_average.py
pyha/cores/packet/__init__.py
pyha/cores/packet/crc16.py
pyha-0.0.14.dist-info/METADATA
pyha-0.0.14.dist-info/RECORD
pyha-0.0.14.dist-info/WHEEL
pyha-0.0.14.dist-info/top_level.txt
