Metadata-Version: 2.1
Name: pyha
Version: 0.0.14
Summary: Pyha
Home-page: https://github.com/gasparka/pyha
Author: Gaspar Karm
Author-email: gkarm@live.com
License: Apache Software License 2.0
Keywords: pyha
Platform: UNKNOWN
Provides-Extra: dev
Requires-Dist: redbaron (==0.7.1)
Requires-Dist: scipy (==1.1.0)
Requires-Dist: numpy (==1.15.1)
Requires-Dist: parse (==1.8.4)
Requires-Dist: six (==1.11.0)
Requires-Dist: tqdm (==4.25.0)
Requires-Dist: scikit-image (==0.14.0)
Requires-Dist: matplotlib (==3.0.0)
Requires-Dist: wurlitzer (==1.0.2)
Provides-Extra: dev
Requires-Dist: bumpversion (==0.5.3); extra == 'dev'
Requires-Dist: wheel (==0.31.1); extra == 'dev'
Requires-Dist: watchdog (==0.9.0); extra == 'dev'
Requires-Dist: flake8 (==3.5.0); extra == 'dev'
Requires-Dist: coverage (==4.5.1); extra == 'dev'
Requires-Dist: Sphinx (==1.8.0); extra == 'dev'
Requires-Dist: sphinx-rtd-theme (==0.4.1); extra == 'dev'
Requires-Dist: twine (==1.11.0); extra == 'dev'
Requires-Dist: sphinx-autobuild (==0.7.1); extra == 'dev'
Requires-Dist: snakeviz (==1.0.0); extra == 'dev'
Requires-Dist: asv (==0.3); extra == 'dev'
Requires-Dist: nbdime (==1.0.2); extra == 'dev'
Requires-Dist: nbval (==0.9.1); extra == 'dev'
Requires-Dist: pytest (==3.8.0); extra == 'dev'
